CHANGELOG.md
LICENSE.txt
README.md
tyrannosaurus/__init__.py
tyrannosaurus/clean.py
tyrannosaurus/cli.py
tyrannosaurus/context.py
tyrannosaurus/enums.py
tyrannosaurus/envs.py
tyrannosaurus/helpers.py
tyrannosaurus/new.py
tyrannosaurus/parser.py
tyrannosaurus/recipes.py
tyrannosaurus/resources/$dotgithub@CODEOWNERS.txt
tyrannosaurus/resources/$dotgithub@settings.yml.txt
tyrannosaurus/resources/$pkg@__init__.py.txt
tyrannosaurus/resources/$pkg@cli.py.txt
tyrannosaurus/resources/CHANGELOG.md.txt
tyrannosaurus/resources/CITATION.cff.txt
tyrannosaurus/resources/CONTRIBUTING.md.txt
tyrannosaurus/resources/Dockerfile.txt
tyrannosaurus/resources/README.md.txt
tyrannosaurus/resources/SECURITY.md.txt
tyrannosaurus/resources/azure-pipelines.yml.txt
tyrannosaurus/resources/codemeta.json.txt
tyrannosaurus/resources/docs@index.rst.txt
tyrannosaurus/resources/pyproject.toml.txt
tyrannosaurus/resources/tests@__init__.py.txt
tyrannosaurus/resources/tests@test_cli.py.txt
tyrannosaurus/resources/tox.ini
tyrannosaurus/sync.py
tyrannosaurus/update.py
tyrannosaurus-0.10.4.dist-info/entry_points.txt
tyrannosaurus-0.10.4.dist-info/LICENSE.txt
tyrannosaurus-0.10.4.dist-info/WHEEL
tyrannosaurus-0.10.4.dist-info/METADATA
tyrannosaurus-0.10.4.dist-info/RECORD
