Metadata-Version: 2.1
Name: tyrannosaurus
Version: 0.10.4
Summary: Generate beautifully modern Python projects with seamless, GitHub-based CI/CD and loads of integrations.
Home-page: https://github.com/dmyersturnbull/tyrannosaurus
License: Apache-2.0
Keywords: python,template,pyproject-toml,python-poetry,conda-build
Author: Douglas Myers-Turnbull
Maintainer: Douglas Myers-Turnbull
Requires-Python: >=3.8,<4
Classifier: Development Status :: 3 - Alpha
Classifier: Environment :: Console
Classifier: Framework :: tox
Classifier: Intended Audience :: Developers
Classifier: License :: OSI Approved :: Apache Software License
Classifier: Natural Language :: English
Classifier: Operating System :: OS Independent
Classifier: Programming Language :: Python :: 3
Classifier: Programming Language :: Python :: 3 :: Only
Classifier: Programming Language :: Python :: 3.10
Classifier: Programming Language :: Python :: 3.8
Classifier: Programming Language :: Python :: 3.9
Classifier: Topic :: Software Development :: Build Tools
Classifier: Topic :: Software Development :: Code Generators
Classifier: Topic :: Software Development :: Libraries :: Python Modules
Requires-Dist: grayskull (>=0.8.5,<1)
Requires-Dist: requests (>=2.24,<3)
Requires-Dist: tomlkit (>=0.7,<1)
Requires-Dist: typer (>=0.3,<1)
Project-URL: CI, https://github.com/dmyersturnbull/tyrannosaurus/actions
Project-URL: Documentation, https://tyrannosaurus.readthedocs.io
Project-URL: Download, https://pypi.org/project/tyrannosaurus/
Project-URL: Issues, https://github.com/dmyersturnbull/tyrannosaurus/issues
Project-URL: Repository, https://github.com/dmyersturnbull/tyrannosaurus
